Metadata-Version: 1.1
Name: prism-mt
Version: 0.0.1
Summary: prism-mt
Home-page: https://github.com/thompsonb/prism
Author: UNKNOWN
Author-email: UNKNOWN
License: UNKNOWN
Platform: UNKNOWN
Classifier: Programming Language :: Python :: 3
Classifier: Operating System :: OS Independent
